.gitignore
.travis.yml
MANIFEST.in
README.rst
bootstrap.py
buildout.cfg
setup.cfg
setup.py
docs/HISTORY.txt
docs/INSTALL.txt
docs/LICENSE.GPL
docs/LICENSE.txt
wildcard/__init__.py
wildcard.cloudflare.egg-info/PKG-INFO
wildcard.cloudflare.egg-info/SOURCES.txt
wildcard.cloudflare.egg-info/dependency_links.txt
wildcard.cloudflare.egg-info/entry_points.txt
wildcard.cloudflare.egg-info/namespace_packages.txt
wildcard.cloudflare.egg-info/not-zip-safe
wildcard.cloudflare.egg-info/requires.txt
wildcard.cloudflare.egg-info/top_level.txt
wildcard/cloudflare/__init__.py
wildcard/cloudflare/browser.py
wildcard/cloudflare/configure.zcml
wildcard/cloudflare/controlpanel_layout.pt
wildcard/cloudflare/interfaces.py
wildcard/cloudflare/purge.pt
wildcard/cloudflare/purger.py
wildcard/cloudflare/tests.py
wildcard/cloudflare/upgrades.py
wildcard/cloudflare/upgrades.zcml
wildcard/cloudflare/profiles/default/actions.xml
wildcard/cloudflare/profiles/default/controlpanel.xml
wildcard/cloudflare/profiles/default/metadata.xml
wildcard/cloudflare/profiles/default/registry.xml
wildcard/cloudflare/tests/__init__.py
wildcard/cloudflare/tests/test_urls.py