Metadata-Version: 2.1
Name: wildcard.cloudflare
Version: 2.1.0
Summary: UNKNOWN
Home-page: https://github.com/collective/wildcard.cloudflare
Author: Nathan Van Gheem
Author-email: nathan@vangheem.us
License: GPL version 2
Keywords: plone caching purging cloudflare
Platform: UNKNOWN
Classifier: Development Status :: 5 - Production/Stable
Classifier: Environment :: Web Environment
Classifier: Framework :: Plone
Classifier: Framework :: Plone :: 4.3
Classifier: Framework :: Plone :: 5.0
Classifier: Framework :: Plone :: 5.2
Classifier: Intended Audience :: System Administrators
Classifier: License :: OSI Approved :: GNU General Public License v2 (GPLv2)
Classifier: Operating System :: OS Independent
Classifier: Programming Language :: Python
Classifier: Programming Language :: Python :: 2.7
Classifier: Programming Language :: Python :: 3.7
Classifier: Topic :: Software Development :: Libraries :: Python Modules
Provides-Extra: test
